MANIFEST.in
README.rst
requirements.txt
setup.py
ece_recorder.egg-info/PKG-INFO
ece_recorder.egg-info/SOURCES.txt
ece_recorder.egg-info/dependency_links.txt
ece_recorder.egg-info/pbr.json
ece_recorder.egg-info/requires.txt
ece_recorder.egg-info/top_level.txt
recorder/__init__.py
recorder/ffmpeg.py
recorder/recorder.py
recorder/system.py
recorder/utils.py
scripts/recorder