Metadata-Version: 1.0
Name: ece-recorder
Version: 0.0.6
Summary: EclipseConEurope recording script
Home-page: www.bitbucket.org/afriemann/ece-recorder.git
Author: Aljosha Friemann
Author-email: aljosha.friemann@gmail.com
License: UNKNOWN
Platform: UNKNOWN
